COPYING
MANIFEST.in
README.md
requirements.txt
setup.py
doc/Makefile
doc/api.rst
doc/conf.py
doc/index.rst
doc/intro.rst
doc/make.bat
rist/__init__.py
rist/_binding.py
rist/common.py
rist/exceptions.py
rist/misc.py
rist/receiver.py
rist/sender.py
rist.egg-info/PKG-INFO
rist.egg-info/SOURCES.txt
rist.egg-info/dependency_links.txt
rist.egg-info/requires.txt
rist.egg-info/top_level.txt