Metadata-Version: 2.1
Name: rist
Version: 0.1.2
Summary: librist Binding
Home-page: https://code.videolan.org/rist/pyrist
Author: Kuldeep Singh Dhaka
Author-email: kuldeep@madresistor.com
License: BSD 2-Clause "Simplified" License
Keywords: RIST librist reliable video stream
Platform: UNKNOWN
Classifier: Development Status :: 3 - Alpha
Classifier: License :: OSI Approved :: BSD License
Classifier: Topic :: Scientific/Engineering
